poly_lithic/__init__.py
poly_lithic/_version.py
poly_lithic/pre_install.py
poly_lithic/scripts/__init__.py
poly_lithic/scripts/main.py
poly_lithic/src/__init__.py
poly_lithic/src/cli.py
poly_lithic/src/config/__init__.py
poly_lithic/src/config/config_object.py
poly_lithic/src/config/parser.py
poly_lithic/src/interfaces/BaseInterface.py
poly_lithic/src/interfaces/__init__.py
poly_lithic/src/interfaces/env.ini
poly_lithic/src/interfaces/file_interface.py
poly_lithic/src/interfaces/k2eg_interface.py
poly_lithic/src/interfaces/p4p_interface.py
poly_lithic/src/logging_utils/__init__.py
poly_lithic/src/logging_utils/make_logger.py
poly_lithic/src/model_utils/LocalModelGetter.py
poly_lithic/src/model_utils/MlflowModelGetter.py
poly_lithic/src/model_utils/ModelGetterBase.py
poly_lithic/src/model_utils/__init__.py
poly_lithic/src/transformers/BaseTransformer.py
poly_lithic/src/transformers/BaseTransformers.py
poly_lithic/src/transformers/CompoundTransformer.py
poly_lithic/src/transformers/__init__.py
poly_lithic/src/utils/__init__.py
poly_lithic/src/utils/builder.py
poly_lithic/src/utils/lazyInterfaceLoader.py
poly_lithic/src/utils/messaging.py
poly_lithic-0.1.7.dist-info/METADATA
poly_lithic-0.1.7.dist-info/WHEEL
poly_lithic-0.1.7.dist-info/entry_points.txt
poly_lithic-0.1.7.dist-info/RECORD
