Metadata-Version: 2.4
Name: poly-lithic
Version: 0.1.7
Summary: A package for deploying AI and other models and more using lume inspired interfaces
Author: Mateusz Leputa, Kathryn Baker, Mihnea Romanovschi, Jesse Bellister
Requires-Dist: boto3>=1.34.65
Requires-Dist: colorlog>=6.8.2
Requires-Dist: k2eg==0.2.7
Requires-Dist: keras>=3.1.1
Requires-Dist: mlflow>=2.12.1
Requires-Dist: numpy<2.0
Requires-Dist: p4p==4.2.0
Requires-Dist: pandas>=2.0.1
Requires-Dist: psutil>=6.0.0
Requires-Dist: psycopg2-binary
Requires-Dist: pyepics==3.5.7
